{
  "subscribers": [
    {
      "email": "test@test.pl",
      "gender": "female",
      "pp-check": "on",
      "id": 1
    },
    {
      "email": "marta.anna.probierz@gmail.com",
      "gender": "female",
      "pp-check": "on",
      "id": 2
    },
    {
      "email": "test@test.com",
      "gender": "male",
      "pp-check": "on",
      "id": 3
    },
    {
      "id": 4
    },
    {
      "email": "marta.probierz@gmail.com",
      "gender": "female",
      "pp-check": "on",
      "id": 5
    },
    {
      "email": "jan-kowalski@test.com",
      "gender": "male",
      "pp-check": "on",
      "id": 6
    },
    {
      "email": "nowak@gmail.com",
      "gender": "female",
      "pp-check": "on",
      "id": 7
    },
    {
      "email": "nowakowska@mail.com",
      "gender": "female",
      "pp-check": "on",
      "id": 8
    }
  ]
}